bufflog/__init__.py
bufflog/bufflog.py
bufflog/datadog.py
python_bufflog-0.1.3.dist-info/LICENSE
python_bufflog-0.1.3.dist-info/METADATA
python_bufflog-0.1.3.dist-info/WHEEL
python_bufflog-0.1.3.dist-info/top_level.txt
python_bufflog-0.1.3.dist-info/RECORD
