Metadata-Version: 2.1
Name: python-bufflog
Version: 0.1.3
Summary: Python logger for Buffer services
Home-page: https://github.com/bufferapp/python-bufflog
Author: David Gasquez
Author-email: davidgasquez@buffer.com
License: UNKNOWN
Platform: UNKNOWN
Requires-Dist: structlog
